ytplaylist/__init__.py
ytplaylist/core.py
YouTubeBrowser-0.0.3.dist-info/LICENSE
YouTubeBrowser-0.0.3.dist-info/METADATA
YouTubeBrowser-0.0.3.dist-info/WHEEL
YouTubeBrowser-0.0.3.dist-info/top_level.txt
YouTubeBrowser-0.0.3.dist-info/RECORD
