Metadata-Version: 2.1
Name: YouTubeBrowser
Version: 0.0.3
Summary: innovata-YouTubeBrowser
Home-page: https://github.com/innovata/YouTubeBrowser
Author: innovata sambong
Author-email: iinnovata@gmail.com
License: UNKNOWN
Platform: UNKNOWN
Classifier: Programming Language :: Python :: 3
Classifier: License :: OSI Approved :: MIT License
Classifier: Operating System :: OS Independent
Requires-Python: >=3.8
License-File: LICENSE
